<?xml version="1.0" encoding="UTF-8"?>
<odoo>
    <record id="ir_cron_sync_prices" model="ir.cron">
        <field name="name">Sincronizar precios personalizados</field>
        <field name="model_id" ref="product.model_product_template"/>
        <field name="state">code</field>
        <field name="code">model.sync_prices_for_customers()</field>
        <field name="interval_number">6</field>
        <field name="interval_type">hours</field>
        <field name="numbercall">-1</field>
        <field name="active" eval="True"/>
    </record>
</odoo>